tmmax/__init__.py
tmmax/__main__.py
tmmax/analysis.py
tmmax/angle.py
tmmax/cascaded_matmul.py
tmmax/data.py
tmmax/fresnel.py
tmmax/plots.py
tmmax/reflect_transmit.py
tmmax/tmm.py
tmmax/wavevector.py
tmmax/nk_data/csv/ALON.csv
tmmax/nk_data/csv/Air.csv
tmmax/nk_data/csv/Al2O3.csv
tmmax/nk_data/csv/CaF2.csv
tmmax/nk_data/csv/CdS.csv
tmmax/nk_data/csv/CdTe.csv
tmmax/nk_data/csv/CeF3.csv
tmmax/nk_data/csv/Ge.csv
tmmax/nk_data/csv/HfO2.csv
tmmax/nk_data/csv/ITO.csv
tmmax/nk_data/csv/Kischkat_Al2O3.csv
tmmax/nk_data/csv/Kischkat_AlN.csv
tmmax/nk_data/csv/Kischkat_Si3N4.csv
tmmax/nk_data/csv/Kischkat_SiO2.csv
tmmax/nk_data/csv/Kischkat_TiO2.csv
tmmax/nk_data/csv/LaF3.csv
tmmax/nk_data/csv/LiF.csv
tmmax/nk_data/csv/MgF2.csv
tmmax/nk_data/csv/MgO.csv
tmmax/nk_data/csv/NaF.csv
tmmax/nk_data/csv/Nb2O5.csv
tmmax/nk_data/csv/PbF2.csv
tmmax/nk_data/csv/Sc2O3.csv
tmmax/nk_data/csv/Si.csv
tmmax/nk_data/csv/Si3N4.csv
tmmax/nk_data/csv/SiO.csv
tmmax/nk_data/csv/SiO2.csv
tmmax/nk_data/csv/SrF2.csv
tmmax/nk_data/csv/Ta2O5.csv
tmmax/nk_data/csv/Te.csv
tmmax/nk_data/csv/TiO2.csv
tmmax/nk_data/csv/Y2O3.csv
tmmax/nk_data/csv/ZnS.csv
tmmax/nk_data/csv/ZnSe.csv
tmmax/nk_data/csv/ZrO2.csv
tmmax/nk_data/numpy/ALON.npy
tmmax/nk_data/numpy/Air.npy
tmmax/nk_data/numpy/Al2O3.npy
tmmax/nk_data/numpy/CaF2.npy
tmmax/nk_data/numpy/CdS.npy
tmmax/nk_data/numpy/CdTe.npy
tmmax/nk_data/numpy/CeF3.npy
tmmax/nk_data/numpy/Ge.npy
tmmax/nk_data/numpy/HfO2.npy
tmmax/nk_data/numpy/ITO.npy
tmmax/nk_data/numpy/Kischkat_Al2O3.npy
tmmax/nk_data/numpy/Kischkat_AlN.npy
tmmax/nk_data/numpy/Kischkat_Si3N4.npy
tmmax/nk_data/numpy/Kischkat_SiO2.npy
tmmax/nk_data/numpy/Kischkat_TiO2.npy
tmmax/nk_data/numpy/LaF3.npy
tmmax/nk_data/numpy/LiF.npy
tmmax/nk_data/numpy/MgF2.npy
tmmax/nk_data/numpy/MgO.npy
tmmax/nk_data/numpy/NaF.npy
tmmax/nk_data/numpy/Nb2O5.npy
tmmax/nk_data/numpy/PbF2.npy
tmmax/nk_data/numpy/Sc2O3.npy
tmmax/nk_data/numpy/Si.npy
tmmax/nk_data/numpy/Si3N4.npy
tmmax/nk_data/numpy/SiO.npy
tmmax-1.1.4.dist-info/licenses/LICENSE
tmmax-1.1.4.dist-info/WHEEL
tmmax-1.1.4.dist-info/METADATA
tmmax-1.1.4.dist-info/RECORD
