Metadata-Version: 2.4
Name: tmmax
Version: 1.1.4
Summary: TMMax: High-performance modeling of multilayer thin-film structures using transfer matrix method with JAX
Keywords: tmm,optics,photonics,jax,thin,film,dielectic,vectorization,jit,coating
Author-email: Bahrem Serhat Danis <bdanis23@ku.edu.tr>
Requires-Python: >=3.10
Classifier: Programming Language :: Python :: 3
Classifier: Programming Language :: Python :: 3 :: Only
Classifier: License :: OSI Approved :: MIT License
Classifier: Operating System :: OS Independent
License-File: LICENSE
Requires-Dist: jax>=0.5.0
Requires-Dist: matplotlib>=3.10.0
Requires-Dist: numpy>=2.2.2
Requires-Dist: pandas>=2.2.3
Requires-Dist: scipy>=1.15.1
Requires-Dist: ruff>=0.6 ; extra == "dev"
Requires-Dist: black>=24.0 ; extra == "dev"
Requires-Dist: pre-commit>=3.6 ; extra == "dev"
Requires-Dist: mypy>=1.10 ; extra == "dev"
Requires-Dist: build>=1.2 ; extra == "dev"
Requires-Dist: twine>=5.0 ; extra == "dev"
Requires-Dist: sphinx==7.1.2 ; extra == "docs"
Requires-Dist: sphinx-rtd-theme==1.3.0rc1 ; extra == "docs"
Requires-Dist: sphinx-favicon==1.0.1 ; extra == "docs"
Requires-Dist: furo==2025.7.19 ; extra == "docs"
Requires-Dist: sphinxcontrib-bibtex ; extra == "docs"
Requires-Dist: nbsphinx ; extra == "docs"
Requires-Dist: nbconvert ; extra == "docs"
Requires-Dist: ipykernel ; extra == "docs"
Requires-Dist: pytest>=8.0 ; extra == "test"
Requires-Dist: pytest-cov>=5.0 ; extra == "test"
Requires-Dist: coverage[toml]>=7.5 ; extra == "test"
Requires-Dist: hypothesis>=6.0 ; extra == "test"
Requires-Dist: tmm==0.2.0 ; extra == "test"
Requires-Dist: matplotlib ; extra == "test"
Project-URL: Documentation, https://tmmax.readthedocs.io/en/latest/
Project-URL: Homepage, https://github.com/bahremsd/tmmax
Project-URL: Issues, https://github.com/bahremsd/tmmax/issues
Project-URL: Repository, https://github.com/bahremsd/tmmax
Provides-Extra: dev
Provides-Extra: docs
Provides-Extra: test
